Workbook

Sheet Данные
A1: Q (Объем туристов) | B1: P (Цена поездки) | C1: V (Переменные затраты) | D1: NCF (Чистый денежный поток) | E1: NPV (Чистая текущая стоимость) | G1: Показатели | I1: Сценарий | L1: Постоянные затраты - F | N1: 500
A2: =RANDBETWEEN(150,300) -> 288 | B2: =RANDBETWEEN(40,55) -> 40 | C2: =RANDBETWEEN(25,35) -> 35 | D2: =(A2*(B2-C2)-$N$1-$N$2)*(1-$N$3)+$N$2 -> 738.4 | E2: =PV($N$4,$N$5,-D2,$N$6,1) -> 1837.186 | I2: минимум | J2: максимум | L2: Амортизация - A | N2: 100
A3: =RANDBETWEEN(150,300) -> 227 | B3: =RANDBETWEEN(40,55) -> 48 | C3: =RANDBETWEEN(25,35) -> 28 | D3: =(A3*(B3-C3)-$N$1-$N$2)*(1-$N$3)+$N$2 -> 3094.4 | E3: =PV($N$4,$N$5,-D3,$N$6,1) -> 11661.389 | G3: общий объем туристов за период - Q | I3: 150 | J3: 300 | L3: Налог на прибыль - T | N3: 0.24
A4: =RANDBETWEEN(150,300) -> 249 | B4: =RANDBETWEEN(40,55) -> 55 | C4: =RANDBETWEEN(25,35) -> 35 | D4: =(A4*(B4-C4)-$N$1-$N$2)*(1-$N$3)+$N$2 -> 3428.8 | E4: =PV($N$4,$N$5,-D4,$N$6,1) -> 13055.792 | G4: общая стоимость туристической поездки - P | I4: 40 | J4: 55 | L4: Норма дисконта - R | N4: 0.1
A5: =RANDBETWEEN(150,300) -> 284 | B5: =RANDBETWEEN(40,55) -> 50 | C5: =RANDBETWEEN(25,35) -> 30 | D5: =(A5*(B5-C5)-$N$1-$N$2)*(1-$N$3)+$N$2 -> 3960.8 | E5: =PV($N$4,$N$5,-D5,$N$6,1) -> 15274.16 | G5: Переменные затраты - V | I5: 25 | J5: 35 | L5: Срок проекта - n | N5: 5
A6: =RANDBETWEEN(150,300) -> 174 | B6: =RANDBETWEEN(40,55) -> 47 | C6: =RANDBETWEEN(25,35) -> 25 | D6: =(A6*(B6-C6)-$N$1-$N$2)*(1-$N$3)+$N$2 -> 2553.28 | E6: =PV($N$4,$N$5,-D6,$N$6,1) -> 9404.9914 | L6: Начальные инвестиции - I0 | N6: 2000
A7: =RANDBETWEEN(150,300) -> 192 | B7: =RANDBETWEEN(40,55) -> 54 | C7: =RANDBETWEEN(25,35) -> 25 | D7: =(A7*(B7-C7)-$N$1-$N$2)*(1-$N$3)+$N$2 -> 3875.68 | E7: =PV($N$4,$N$5,-D7,$N$6,1) -> 14919.221
A8: =RANDBETWEEN(150,300) -> 254 | B8: =RANDBETWEEN(40,55) -> 44 | C8: =RANDBETWEEN(25,35) -> 26 | D8: =(A8*(B8-C8)-$N$1-$N$2)*(1-$N$3)+$N$2 -> 3118.72 | E8: =PV($N$4,$N$5,-D8,$N$6,1) -> 11762.8
A9: =RANDBETWEEN(150,300) -> 164 | B9: =RANDBETWEEN(40,55) -> 49 | C9: =RANDBETWEEN(25,35) -> 29 | D9: =(A9*(B9-C9)-$N$1-$N$2)*(1-$N$3)+$N$2 -> 2136.8 | E9: =PV($N$4,$N$5,-D9,$N$6,1) -> 7668.3258
A10: =RANDBETWEEN(150,300) -> 258 | B10: =RANDBETWEEN(40,55) -> 43 | C10: =RANDBETWEEN(25,35) -> 30 | D10: =(A10*(B10-C10)-$N$1-$N$2)*(1-$N$3)+$N$2 -> 2193.04 | E10: =PV($N$4,$N$5,-D10,$N$6,1) -> 7902.8391
A11: =RANDBETWEEN(150,300) -> 150 | B11: =RANDBETWEEN(40,55) -> 49 | C11: =RANDBETWEEN(25,35) -> 31 | D11: =(A11*(B11-C11)-$N$1-$N$2)*(1-$N$3)+$N$2 -> 1696 | E11: =PV($N$4,$N$5,-D11,$N$6,1) -> 5830.2492
A12: =RANDBETWEEN(150,300) -> 267 | B12: =RANDBETWEEN(40,55) -> 43 | C12: =RANDBETWEEN(25,35) -> 25 | D12: =(A12*(B12-C12)-$N$1-$N$2)*(1-$N$3)+$N$2 -> 3296.56 | E12: =PV($N$4,$N$5,-D12,$N$6,1) -> 12504.369
A13: =RANDBETWEEN(150,300) -> 232 | B13: =RANDBETWEEN(40,55) -> 44 | C13: =RANDBETWEEN(25,35) -> 30 | D13: =(A13*(B13-C13)-$N$1-$N$2)*(1-$N$3)+$N$2 -> 2112.48 | E13: =PV($N$4,$N$5,-D13,$N$6,1) -> 7566.9147
A14: =RANDBETWEEN(150,300) -> 298 | B14: =RANDBETWEEN(40,55) -> 40 | C14: =RANDBETWEEN(25,35) -> 33 | D14: =(A14*(B14-C14)-$N$1-$N$2)*(1-$N$3)+$N$2 -> 1229.36 | E14: =PV($N$4,$N$5,-D14,$N$6,1) -> 3884.4231
A15: =RANDBETWEEN(150,300) -> 176 | B15: =RANDBETWEEN(40,55) -> 52 | C15: =RANDBETWEEN(25,35) -> 31 | D15: =(A15*(B15-C15)-$N$1-$N$2)*(1-$N$3)+$N$2 -> 2452.96 | E15: =PV($N$4,$N$5,-D15,$N$6,1) -> 8986.6705 | G15: статистические характеристики проекта
A16: =RANDBETWEEN(150,300) -> 268 | B16: =RANDBETWEEN(40,55) -> 54 | C16: =RANDBETWEEN(25,35) -> 33 | D16: =(A16*(B16-C16)-$N$1-$N$2)*(1-$N$3)+$N$2 -> 3921.28 | E16: =PV($N$4,$N$5,-D16,$N$6,1) -> 15109.367 | G16: Метрика | H16: Q | I16: P | J16: V | K16: NCF | L16: NPV
A17: =RANDBETWEEN(150,300) -> 251 | B17: =RANDBETWEEN(40,55) -> 40 | C17: =RANDBETWEEN(25,35) -> 32 | D17: =(A17*(B17-C17)-$N$1-$N$2)*(1-$N$3)+$N$2 -> 1170.08 | E17: =PV($N$4,$N$5,-D17,$N$6,1) -> 3637.2335 | G17: Среднее | H17: =AVERAGE($A$2:$A$501) -> 226.15 | I17: =AVERAGE($B$2:$B$501) -> 47.67 | J17: =AVERAGE($C$2:$C$501) -> 29.846 | K17: =AVERAGE($D$2:$D$501) -> 2710.5118 | L17: =AVERAGE($E$2:$E$501) -> 10060.627
A18: =RANDBETWEEN(150,300) -> 202 | B18: =RANDBETWEEN(40,55) -> 53 | C18: =RANDBETWEEN(25,35) -> 25 | D18: =(A18*(B18-C18)-$N$1-$N$2)*(1-$N$3)+$N$2 -> 3942.56 | E18: =PV($N$4,$N$5,-D18,$N$6,1) -> 15198.102 | G18: Минимум | H18: =MIN($A$2:$A$501) -> 150 | I18: =MIN($B$2:$B$501) -> 40 | J18: =MIN($C$2:$C$501) -> 25 | K18: =MIN($D$2:$D$501) -> 328 | L18: =MIN($E$2:$E$501) -> 125.87322
A19: =RANDBETWEEN(150,300) -> 259 | B19: =RANDBETWEEN(40,55) -> 53 | C19: =RANDBETWEEN(25,35) -> 25 | D19: =(A19*(B19-C19)-$N$1-$N$2)*(1-$N$3)+$N$2 -> 5155.52 | E19: =PV($N$4,$N$5,-D19,$N$6,1) -> 20255.982 | G19: Максимум | H19: =MAX($A$2:$A$501) -> 300 | I19: =MAX($B$2:$B$501) -> 55 | J19: =MAX($C$2:$C$501) -> 35 | K19: =MAX($D$2:$D$501) -> 6101.72 | L19: =MAX($E$2:$E$501) -> 24201.509
A20: =RANDBETWEEN(150,300) -> 239 | B20: =RANDBETWEEN(40,55) -> 49 | C20: =RANDBETWEEN(25,35) -> 25 | D20: =(A20*(B20-C20)-$N$1-$N$2)*(1-$N$3)+$N$2 -> 4003.36 | E20: =PV($N$4,$N$5,-D20,$N$6,1) -> 15451.63 | G20: Станд. отклонение | H20: =STDEV($A$2:$A$501) -> 44.023171 | I20: =STDEV($B$2:$B$501) -> 4.6785551 | J20: =STDEV($C$2:$C$501) -> 3.1224643 | K20: =STDEV($D$2:$D$501) -> 1189.5098 | L20: =STDEV($E$2:$E$501) -> 4960.0957
A21: =RANDBETWEEN(150,300) -> 154 | B21: =RANDBETWEEN(40,55) -> 43 | C21: =RANDBETWEEN(25,35) -> 32 | D21: =(A21*(B21-C21)-$N$1-$N$2)*(1-$N$3)+$N$2 -> 931.44 | E21: =PV($N$4,$N$5,-D21,$N$6,1) -> 2642.1368 | G21: Кол-во убыточных NPV | H21: - | I21: - | J21: - | K21: - | L21: =COUNTIF($E$2:$E$501, "<0") -> 0
A22: =RANDBETWEEN(150,300) -> 169 | B22: =RANDBETWEEN(40,55) -> 50 | C22: =RANDBETWEEN(25,35) -> 33 | D22: =(A22*(B22-C22)-$N$1-$N$2)*(1-$N$3)+$N$2 -> 1827.48 | E22: =PV($N$4,$N$5,-D22,$N$6,1) -> 6378.5031 | G22: Вероятность убыточности | H22: - | I22: - | J22: - | K22: - | L22: =COUNTIF($E$2:$E$501, "<0")/500 -> 0
A23: =RANDBETWEEN(150,300) -> 245 | B23: =RANDBETWEEN(40,55) -> 51 | C23: =RANDBETWEEN(25,35) -> 32 | D23: =(A23*(B23-C23)-$N$1-$N$2)*(1-$N$3)+$N$2 -> 3181.8 | E23: =PV($N$4,$N$5,-D23,$N$6,1) -> 12025.835
A24: =RANDBETWEEN(150,300) -> 156 | B24: =RANDBETWEEN(40,55) -> 47 | C24: =RANDBETWEEN(25,35) -> 29 | D24: =(A24*(B24-C24)-$N$1-$N$2)*(1-$N$3)+$N$2 -> 1778.08 | E24: =PV($N$4,$N$5,-D24,$N$6,1) -> 6172.5117
A25: =RANDBETWEEN(150,300) -> 274 | B25: =RANDBETWEEN(40,55) -> 42 | C25: =RANDBETWEEN(25,35) -> 26 | D25: =(A25*(B25-C25)-$N$1-$N$2)*(1-$N$3)+$N$2 -> 2975.84 | E25: =PV($N$4,$N$5,-D25,$N$6,1) -> 11167.01 | G25: графическая интерпретация результатов
A26: =RANDBETWEEN(150,300) -> 248 | B26: =RANDBETWEEN(40,55) -> 54 | C26: =RANDBETWEEN(25,35) -> 35 | D26: =(A26*(B26-C26)-$N$1-$N$2)*(1-$N$3)+$N$2 -> 3225.12 | E26: =PV($N$4,$N$5,-D26,$N$6,1) -> 12206.474
A27: =RANDBETWEEN(150,300) -> 262 | B27: =RANDBETWEEN(40,55) -> 41 | C27: =RANDBETWEEN(25,35) -> 28 | D27: =(A27*(B27-C27)-$N$1-$N$2)*(1-$N$3)+$N$2 -> 2232.56 | E27: =PV($N$4,$N$5,-D27,$N$6,1) -> 8067.6322
A28: =RANDBETWEEN(150,300) -> 217 | B28: =RANDBETWEEN(40,55) -> 47 | C28: =RANDBETWEEN(25,35) -> 25 | D28: =(A28*(B28-C28)-$N$1-$N$2)*(1-$N$3)+$N$2 -> 3272.24 | E28: =PV($N$4,$N$5,-D28,$N$6,1) -> 12402.958
A29: =RANDBETWEEN(150,300) -> 293 | B29: =RANDBETWEEN(40,55) -> 54 | C29: =RANDBETWEEN(25,35) -> 34 | D29: =(A29*(B29-C29)-$N$1-$N$2)*(1-$N$3)+$N$2 -> 4097.6 | E29: =PV($N$4,$N$5,-D29,$N$6,1) -> 15844.598
A30: =RANDBETWEEN(150,300) -> 291 | B30: =RANDBETWEEN(40,55) -> 54 | C30: =RANDBETWEEN(25,35) -> 26 | D30: =(A30*(B30-C30)-$N$1-$N$2)*(1-$N$3)+$N$2 -> 5836.48 | E30: =PV($N$4,$N$5,-D30,$N$6,1) -> 23095.494
A31: =RANDBETWEEN(150,300) -> 266 | B31: =RANDBETWEEN(40,55) -> 54 | C31: =RANDBETWEEN(25,35) -> 31 | D31: =(A31*(B31-C31)-$N$1-$N$2)*(1-$N$3)+$N$2 -> 4293.68 | E31: =PV($N$4,$N$5,-D31,$N$6,1) -> 16662.225
A32: =RANDBETWEEN(150,300) -> 199 | B32: =RANDBETWEEN(40,55) -> 43 | C32: =RANDBETWEEN(25,35) -> 30 | D32: =(A32*(B32-C32)-$N$1-$N$2)*(1-$N$3)+$N$2 -> 1610.12 | E32: =PV($N$4,$N$5,-D32,$N$6,1) -> 5472.1411
A33: =RANDBETWEEN(150,300) -> 151 | B33: =RANDBETWEEN(40,55) -> 49 | C33: =RANDBETWEEN(25,35) -> 25 | D33: =(A33*(B33-C33)-$N$1-$N$2)*(1-$N$3)+$N$2 -> 2398.24 | E33: =PV($N$4,$N$5,-D33,$N$6,1) -> 8758.4955
A34: =RANDBETWEEN(150,300) -> 182 | B34: =RANDBETWEEN(40,55) -> 46 | C34: =RANDBETWEEN(25,35) -> 30 | D34: =(A34*(B34-C34)-$N$1-$N$2)*(1-$N$3)+$N$2 -> 1857.12 | E34: =PV($N$4,$N$5,-D34,$N$6,1) -> 6502.0979
A35: =RANDBETWEEN(150,300) -> 222 | B35: =RANDBETWEEN(40,55) -> 49 | C35: =RANDBETWEEN(25,35) -> 26 | D35: =(A35*(B35-C35)-$N$1-$N$2)*(1-$N$3)+$N$2 -> 3524.56 | E35: =PV($N$4,$N$5,-D35,$N$6,1) -> 13455.098
A36: =RANDBETWEEN(150,300) -> 296 | B36: =RANDBETWEEN(40,55) -> 49 | C36: =RANDBETWEEN(25,35) -> 30 | D36: =(A36*(B36-C36)-$N$1-$N$2)*(1-$N$3)+$N$2 -> 3918.24 | E36: =PV($N$4,$N$5,-D36,$N$6,1) -> 15096.691
A37: =RANDBETWEEN(150,300) -> 183 | B37: =RANDBETWEEN(40,55) -> 43 | C37: =RANDBETWEEN(25,35) -> 33 | D37: =(A37*(B37-C37)-$N$1-$N$2)*(1-$N$3)+$N$2 -> 1034.8 | E37: =PV($N$4,$N$5,-D37,$N$6,1) -> 3073.1341
... A501: =RANDBETWEEN(150,300) -> 222 | B501: =RANDBETWEEN(40,55) -> 53 | C501: =RANDBETWEEN(25,35) -> 26 | D501: =(A501*(B501-C501)-$N$1-$N$2)*(1-$N$3)+$N$2 -> 4199.44 | E501: =PV($N$4,$N$5,-D501,$N$6,1) -> 16269.257

Sheet Статистика
A1: Показатели | C1: Сценарий | F1: Постоянные затраты - F | H1: 500 | I1: 1 | J1: n | K1: 1 | L1: 2 | M1: 5 | N1: 7 | O1: 9 | P1: 14
C2: минимум | D2: максимум | F2: Амортизация - A | H2: 100 | J2: p | K2: 0.012689485 | L2: 0.012148485 | M2: 0.010386514 | N2: 0.010388708 | O2: 0.0096919896 | P2: 0.0087909614
A3: общий объем туристов за период - Q | C3: 150 | D3: 300 | F3: Налог на прибыль - T | H3: 0.24
A4: общая стоимость туристической поездки - P | C4: 40 | D4: 55 | F4: Норма дисконта - R | H4: 0.1 | I4: 2 | J4: n | K4: 10 | L4: 15 | M4: 20 | N4: 30 | O4: 40 | P4: 50
A5: Переменные затраты - V | C5: 25 | D5: 35 | F5: Срок проекта - n | H5: 5 | J5: p | K5: 0.01195008 | L5: 0.010834391 | M5: 0.0088008494 | N5: 0.0088816645 | O5: 0.0075925571 | P5: 0.0060217066
F6: Начальные инвестиции - I0 | H6: 2000
I7: 3 | J7: n | K7: 0.1 | L7: 0.3 | M7: 0.56 | N7: 0.78 | O7: 0.87 | P7: 0.99
J8: p | K8: 0.012963618 | L8: 0.010250857 | M8: 0.010174493 | N8: 0.0090385053 | O8: 0.0077993186 | P8: 0.0070568204
C9: Показатели | D9: Перем. Расх(V) | E9: Кол-во(Q) | F9: Цена(P) | G9: Поступление(NCFt) | H9: (NVPt)
C10: Среднее знач. | D10: =AVERAGE(Данные!A2:A508) -> 226.15 | E10: =AVERAGE(Данные!B2:B508) -> 47.67 | F10: =AVERAGE(Данные!C2:C508) -> 29.846 | G10: =AVERAGE(Данные!D2:D508) -> 2710.5118 | H10: =AVERAGE(Данные!E2:E508) -> 10060.627 | I10: 4 | J10: n | K10: 80 | L10: 100 | M10: 120 | N10: 130 | O10: 140 | P10: 150
C11: Станд_откл | D11: =STDEV(Данные!A2:A508) -> 44.023171 | E11: =STDEV(Данные!B2:B508) -> 4.6785551 | F11: =STDEV(Данные!C2:C508) -> 3.1224643 | G11: =STDEV(Данные!D2:D508) -> 1189.5098 | H11: =STDEV(Данные!E2:E508) -> 4960.0957 | J11: p | K11: 0.0092292313 | L11: 0.0081108504 | M11: 0.0079790523 | N11: 0.0072534672 | O11: 0.0061315165 | P11: 0.0054502489
C12: Коэф_вар | D12: =D11/D10 -> 0.19466359 | E12: =E11/E10 -> 0.098144642 | F12: =F11/F10 -> 0.10461919 | G12: =G11/G10 -> 0.43885061 | H12: =H11/H10 -> 0.49302053
C13: Минимум | D13: =MIN(Данные!A2:A508) -> 150 | E13: =MIN(Данные!B2:B508) -> 40 | F13: =MIN(Данные!C2:C508) -> 25 | G13: =MIN(Данные!D2:D508) -> 328 | H13: =MIN(Данные!E2:E508) -> 125.87322 | I13: 5 | J13: n | K13: 13 | L13: 17 | M13: 23 | N13: 28 | O13: 31 | P13: 40
C14: Максимум | D14: =MAX(Данные!A2:A508) -> 300 | E14: =MAX(Данные!B2:B508) -> 55 | F14: =MAX(Данные!C2:C508) -> 35 | G14: =MAX(Данные!D2:D508) -> 6101.72 | H14: =MAX(Данные!E2:E508) -> 24201.509 | J14: p | K14: 0.01305008 | L14: 0.012454016 | M14: 0.011684593 | N14: 0.011142599 | O14: 0.010964402 | P14: 0.010534345
C15: Число случ. NPV<0 | H15: =COUNTIF(Данные!E2:E508,"<0") -> 0
C16: Сумма убытков | H16: =SUMIF(Данные!E2:E500,">0") -> 5014044.3 | J16: Таблица выборки результатов работы модели
C17: Сумма доходов | H17: =SUMIF(Данные!E3:E501,">0") -> 5028476.3
C19: Вероятность p(NPV<=X) | E19: Величина x | F19: Нормал. (x) | G19: p(NPV<=x) | H19: Вероятность NPV<0
E20: 0 | F20: =STANDARDIZE(0,H10,H11) -> -2.0283131 | G20: =NORMSDIST(F20) -> 0.021264151 | H20: =NORMSDIST(F20) -> 0.021264151
C24: дополнительные статистические характеристики инвестиционного проекта
C25: V | E25: Q | G25: P | I25: NCFt | K25: NVPt
C27: Среднее | D27: 222.114 | E27: Среднее | F27: 47.272 | G27: Среднее | H27: 29.846 | I27: Среднее | J27: 2624.9602 | K27: Среднее | L27: 11020.876
C28: Стандартная ошибка | D28: 1.9430453 | E28: Стандартная ошибка | F28: 0.2069824 | G28: Стандартная ошибка | H28: 0.1438818 | I28: Стандартная ошибка | J28: 51.64619 | K28: Стандартная ошибка | L28: 216.92048
C29: Медиана | D29: 219 | E29: Медиана | F29: 47 | G29: Медиана | H29: 30 | I29: Медиана | J29: 2538.08 | K29: Медиана | L29: 10399.644
C30: Мода | D30: 221 | E30: Мода | F30: 52 | G30: Мода | H30: 27 | I30: Мода | J30: 1650.4 | K30: Мода | L30: 13575.08
C31: Стандартное отклонение | D31: 43.447813 | E31: Стандартное отклонение | F31: 4.6282672 | G31: Стандартное отклонение | H31: 3.2172948 | I31: Стандартное отклонение | J31: 1154.8439 | K31: Стандартное отклонение | L31: 4850.4894
C32: Дисперсия выборки | D32: 1887.7124 | E32: Дисперсия выборки | F32: 21.420858 | G32: Дисперсия выборки | H32: 10.350986 | I32: Дисперсия выборки | J32: 1333664.5 | K32: Дисперсия выборки | L32: 23527248
C33: Эксцесс | D33: -1.2030936 | E33: Эксцесс | F33: -1.2606623 | G33: Эксцесс | H33: -1.2468735 | I33: Эксцесс | J33: -0.16381798 | K33: Эксцесс | L33: 0.039858399
C34: Асимметричность | D34: 0.12368349 | E34: Асимметричность | F34: 0.042653742 | G34: Асимметричность | H34: 0.11425811 | I34: Асимметричность | J34: 0.44838583 | K34: Асимметричность | L34: 0.500637
C35: Интервал | D35: 148 | E35: Интервал | F35: 15 | G35: Интервал | H35: 10 | I35: Интервал | J35: 5829.96 | K35: Интервал | L35: 24589.029
C36: Минимум | D36: 152 | E36: Минимум | F36: 40 | G36: Минимум | H36: 25 | I36: Минимум | J36: 293.8 | K36: Минимум | L36: 1405.745
C37: Максимум | D37: 300 | E37: Максимум | F37: 55 | G37: Максимум | H37: 35 | I37: Максимум | J37: 6123.76 | K37: Максимум | L37: 25994.774
C38: Сумма | D38: 111057 | E38: Сумма | F38: 23636 | G38: Сумма | H38: 14923 | I38: Сумма | J38: 1312480.1 | K38: Сумма | L38: 5510438.2
C39: Счет | D39: 500 | E39: Счет | F39: 500 | G39: Счет | H39: 500 | I39: Счет | J39: 500 | K39: Счет | L39: 500
D43: V | E43: Q | F43: P | G43: NCFt | H43: NVPt
C44: V | D44: 1
C45: Q | D45: 0.075812015 | E45: 1
C46: P | D46: -0.0036653697 | E46: -0.075533702 | F46: 1
C47: NCFt | D47: 0.52315733 | E47: 0.69056324 | F47: -0.47936442 | G47: 1
C48: NVPt | D48: 0.52102628 | E48: 0.68940311 | F48: -0.50535315 | G48: 1 | H48: 1
